<?xml version="1.0" encoding="UTF-8"?>

<DocumentationHtmls xmlns:xsi="http://www.w3.org/2001/XMLSchema-instance" xsi:noNamespaceSchemaLocation="opencms://system/modules/com.alkacon.opencms.documentation/schemas/documentation-html.xsd">
  <DocumentationHtml language="en">
    <Html name="Html0">
      <links>
        <link name="link0" internal="true" type="IMG">
          <target><![CDATA[/sites/default/opencms-documentation/.galleries/icons_big/copyLocaleBigIconActive.png]]></target>
          <uuid>7b88d64c-02bc-11e4-8167-1305b26fecac</uuid>
          <query><![CDATA[__scale=h:14,w:14,c:transparent]]></query>
        </link>
        <link name="link1" internal="true" type="IMG">
          <target><![CDATA[/sites/default/opencms-documentation/.galleries/icons_big/deleteLocaleBigIconActive.png]]></target>
          <uuid>7b8f660c-02bc-11e4-8167-1305b26fecac</uuid>
          <query><![CDATA[__scale=h:14,w:14,c:transparent]]></query>
        </link>
        <link name="link2" internal="true" type="A">
          <target><![CDATA[/sites/default/opencms-documentation/background/localization/]]></target>
          <anchor><![CDATA[sec_content_localization]]></anchor>
        </link>
      </links>
      <content><![CDATA[<p>When you edit a content, you can potentially always edit it in multiple languages. But, when you create a new content, it is created only in one language. This language depends on the locale of the page where you add the content. E.g., if you add a content on an english page, it will be available in English.</p>
<p>If you want provide your content in more than one language you can:</p>
<ul>
<li><em>Add a new language version with default values</em>: In the form-based editor's toolbar, you can switch the language. If a language is marked by "[-]" in the language selector, it does not exist yet. It is created with the default values if you switch to that language.</li>
<li><em>Copy the values of your currently edited language to another language</em>: Use the "Copy locale" option (<img style="width: 14px;" title="copyLocaleBigIconActive" src="%(link0)" alt="" />) from the toolbar and select to which language you want to copy the values from the current language to. With the "Copy locale" function, you can also overwrite already existing language versions.</li>
<li><em>Delete an exisiting language version</em>: If more than one language version is present, you can delete language versions. To do so, switch to the language you want to delete and press "Delete locale" (<img style="width: 14px;" title="deleteLocaleBigIconActive" src="%(link1)" alt="" />) in the toolbar.</li>
</ul>
<div class="alert alert-info">The languages available in the content editor are configured as describe <a href="%(link2)">here</a>.</div>]]></content>
    </Html>
  </DocumentationHtml>
</DocumentationHtmls>
