<?xml version="1.0" encoding="UTF-8"?>

<DocumentationHtmls xmlns:xsi="http://www.w3.org/2001/XMLSchema-instance" xsi:noNamespaceSchemaLocation="opencms://system/modules/com.alkacon.opencms.documentation/schemas/documentation-html.xsd">
  <DocumentationHtml language="en">
    <Html name="Html0">
      <links>
        <link name="link0" internal="false" type="A">
          <target><![CDATA[http://pub-docu/opencms-documentation/creating-a-website/creating-template-models/]]></target>
        </link>
      </links>
      <content><![CDATA[<p>Go to the sitemap editor in the (sub-)site using your template. Choose the view "Templates" and adjust either the already existing template model(s) or add new owns. Template models are the master copy used when creating new pages via the sitemap editor. The models can already have set specific properties and contain content that should be placed on all pages created by the model.</p>
<ul>
<li><a href="%(link0)">Learn how to create and use template models.</a></li>
</ul>]]></content>
    </Html>
  </DocumentationHtml>
</DocumentationHtmls>
