<?xml version="1.0" encoding="UTF-8"?>

<DocumentationHtmls xmlns:xsi="http://www.w3.org/2001/XMLSchema-instance" xsi:noNamespaceSchemaLocation="opencms://system/modules/com.alkacon.opencms.documentation/schemas/documentation-html.xsd">
  <DocumentationHtml language="en">
    <Html name="Html0">
      <links/>
      <content><![CDATA[<p>Element views can be added by modules. Thus, many different element views may exist, but you may not want to show all of them to all users.</p>
<p>Thus, element views can only be selected via the page editor if:</p>
<ul>
<li>The user has permissions to see the element view at all.</li>
<li>The view is non-empty for the current page, i.e., at least one resource type is configured to be in the view via the sitemap or module configuration.</li>
</ul>]]></content>
    </Html>
  </DocumentationHtml>
</DocumentationHtmls>
