<?xml version="1.0" encoding="UTF-8"?>

<DocumentationHtmls xmlns:xsi="http://www.w3.org/2001/XMLSchema-instance" xsi:noNamespaceSchemaLocation="opencms://system/modules/com.alkacon.opencms.documentation/schemas/documentation-html.xsd">
  <DocumentationHtml language="en">
    <Html name="Html0">
      <links>
        <link name="link0" internal="true" type="A">
          <target><![CDATA[/sites/default/opencms-documentation/background/the-virtual-file-system/]]></target>
          <uuid>a39f771c-2793-11e4-b2bf-49dbf0abad32</uuid>
          <anchor><![CDATA[properties]]></anchor>
        </link>
      </links>
      <content><![CDATA[<p>Up to now, we have translated contents. But, e.g., the navigation on the pages is build using page properties. In particular <code>NavText</code> and <code>Title</code> are used. <a href="%(link0)">Properties in OpenCms</a> are unilingual by nature. To read properties locale-specific, OpenCms 10.5 introduces a mechanism to simulate multilingual properties. Property names can be extended by a locale specific postfix and then be read locale specific.</p>
<p>For example, besides the property <code>Title</code>, we can add the properties <code>Title_de</code> and <code>Title_fr</code>. If we request the <code>Title</code> property for German, we get the value of <code>Title_de</code>. If we request it for French, we get the value of <code>Title_fr</code>. If we request it in English we get <code>Title</code>, since <code>Title_en</code> is not provided.</p>
<p>We use the multilingual properties to localize <code>Title</code> and <code>NavText</code> in the tutorial.</p>
<p>First we need to add property configurations for <code>Title_de</code>, <code>Title_fr</code>, <code>NavText_de</code> and <code>NavText_fr</code> to the sitemap configuration. Open the Sitemap editor in the Sitemap view and select "Advanced" -&gt; "Sitemap configuration". Below, you see part of the configurations to add. Check the "Prefer folder" option for <code>NavText</code> properties. If checked, properties are added to the folder of a page instead of adding it to the index.html.</p>]]></content>
    </Html>
  </DocumentationHtml>
</DocumentationHtmls>
