<?xml version="1.0" encoding="UTF-8"?>

<DocumentationHtmls xmlns:xsi="http://www.w3.org/2001/XMLSchema-instance" xsi:noNamespaceSchemaLocation="opencms://system/modules/com.alkacon.opencms.documentation/schemas/documentation-html.xsd">
  <DocumentationHtml language="en">
    <Html name="Html0">
      <links>
        <link name="link0" internal="true" type="A">
          <target><![CDATA[/sites/default/opencms-documentation/content-in-opencms/defining-a-content-type/defining-the-contents-behavior/search-settings/]]></target>
          <uuid>bb7a2160-65a5-11e4-9296-005056b61161</uuid>
        </link>
      </links>
      <content><![CDATA[<p>Dynamic fields are fields where you declare only a template for the fields name and thereby allow for all fields that follow the template. Dynamic fields are declared like:</p>
<ul>
<li><strong>*_{suffix}</strong> - what allows for all fields named {my special field name}_{suffix}, e.g., if the declaration is <code>*_de</code>, the fields <code>content_de</code>, <code>special_value_de</code>, ... are allowed.</li>
<li><strong>{prefix}_*</strong> - what allows for all fields named {prefix}_{my special field name}, e.g., if the declaration is <code>de_*</code>, the fields <code>de_excerpt</code>, <code>de_special_value</code>, ... are allowed.</li>
</ul>
<p>The great thing is, that you can add new fields without altering the schema. This is heavily used by OpenCms, e.g., when</p>
<ul>
<li>indexing properties (with <code>*_prop</code>, <code>*_dprop</code>, <code>*_prop_s</code>, ...)</li>
<li>allowing for <a href="%(link0)">search settings for XML contents</a></li>
<li>...</li>
</ul>]]></content>
    </Html>
  </DocumentationHtml>
</DocumentationHtmls>
