<?xml version="1.0" encoding="UTF-8"?>

<DocumentationHtmls xmlns:xsi="http://www.w3.org/2001/XMLSchema-instance" xsi:noNamespaceSchemaLocation="opencms://system/modules/com.alkacon.opencms.documentation/schemas/documentation-html.xsd">
  <DocumentationHtml language="en">
    <Html name="Html0">
      <links/>
      <content><![CDATA[<p>The websites app is mainly a tool for manipulating the <code>opencms-sites.xml</code>. If you like to have your site configuration automatically set up. You can adjust the file directly as well.</p>]]></content>
    </Html>
  </DocumentationHtml>
</DocumentationHtmls>
