<?xml version="1.0" encoding="UTF-8"?>

<DocumentationHtmls xmlns:xsi="http://www.w3.org/2001/XMLSchema-instance" xsi:noNamespaceSchemaLocation="opencms://system/modules/com.alkacon.opencms.documentation/schemas/documentation-html.xsd">
  <DocumentationHtml language="en">
    <Html name="Html0">
      <links/>
      <content><![CDATA[<p>Collect data in a form, which can appear on several pages of the website. Display the results of the user request on one page in the navigation. For example, integration of a search form on several pages of the website and displaying of the search results on one page in the navigation. Since OpenCms 8.0.3 you can use function detail page to define such result pages.</p>]]></content>
    </Html>
  </DocumentationHtml>
</DocumentationHtmls>
