<?xml version="1.0" encoding="UTF-8"?>

<AlkaconDocumentationGlossarEntrys xmlns:xsi="http://www.w3.org/2001/XMLSchema-instance" xsi:noNamespaceSchemaLocation="opencms://system/modules/com.alkacon.opencms.documentation/schemas/documentation-glossar-entry.xsd">
  <AlkaconDocumentationGlossarEntry language="en">
    <Term><![CDATA[Solr field]]></Term>
    <RefId><![CDATA[solr_field]]></RefId>
    <Synonym><![CDATA[Solr index field]]></Synonym>
    <Synonym><![CDATA[index field, Solr]]></Synonym>
    <Match><![CDATA[Solr field]]></Match>
    <Match><![CDATA[Solr index field]]></Match>
    <Description name="Description0">
      <links/>
      <content><![CDATA[<p>A Solr (index) field describes a field in the Solr search index.</p>]]></content>
    </Description>
  </AlkaconDocumentationGlossarEntry>
</AlkaconDocumentationGlossarEntrys>
