<?xml version="1.0" encoding="UTF-8"?>

<LinkSequenceData xmlns:xsi="http://www.w3.org/2001/XMLSchema-instance" xsi:noNamespaceSchemaLocation="opencms://system/modules/alkacon.mercury.template/schemas/linksequence.xsd">
  <LinkSequence language="en">
    <Title><![CDATA[Related Links]]></Title>
    <LinkEntry>
      <Text><![CDATA[A demo on meta mappings]]></Text>
      <URI>
        <link internal="true" type="WEAK">
          <target><![CDATA[/sites/docu/opencms-documentation/todo/demos/meta-mappings/]]></target>
          <uuid>63e8e147-d1cd-11ec-9238-0242ac11002b</uuid>
        </link>
      </URI>
    </LinkEntry>
    <LinkEntry>
      <Text><![CDATA[Further information on SEO]]></Text>
      <URI>
        <link internal="true" type="WEAK">
          <target><![CDATA[/sites/docu/opencms-documentation/creating-a-website/search-engine-optimization-seo/]]></target>
          <uuid>d7d54cbc-d1c7-11ec-9238-0242ac11002b</uuid>
        </link>
      </URI>
    </LinkEntry>
  </LinkSequence>
</LinkSequenceData>
