<?xml version="1.0" encoding="UTF-8"?>

<AlkaconDocumentationTopicFrames xmlns:xsi="http://www.w3.org/2001/XMLSchema-instance" xsi:noNamespaceSchemaLocation="opencms://system/modules/com.alkacon.opencms.documentation/schemas/documentation-topic.xsd">
  <AlkaconDocumentationTopicFrame language="en">
    <Overview name="Overview0">
      <links/>
      <content><![CDATA[<p>When building lists of content, it's a typical requirement to link from a condensed view of the content to a more detailed view. For example, in a list of news, only title, teaser and maybe a date and author are displayed. You click on a news to get to a page showing the complete news article. Similarly, events, products or any other type of resource/content may be shown in a list with links to a detailed views added.</p>
<p>In OpenCms it is sufficient to <em>create and configure one</em> page to automatically <em>get all pages</em> for the detailed views of each content of a type - each under a separate, nice and configurable URL and even editable. The configured page is called detail page and since OpenCms 11, it is even possible to configure only one detail page for the detail views of contents of all types.</p>
<p>In this topic you learn how to configure a detail page, the special container tag attributes related to detail pages and how to link to a detail page.</p>]]></content>
    </Overview>
    <Teaser name="Teaser0">
      <links/>
      <content><![CDATA[<p>You need to link from a condensed view of your contents, e.g., in a list, to a page showing all the content's details? With OpenCms' detail page mechanism you create and configure only one page to get pages for all your contents automatically.</p>]]></content>
    </Teaser>
    <Keywords><![CDATA[content, XML, list, detail page, detail only, default detail page]]></Keywords>
    <InterestingFor><![CDATA[c_developer]]></InterestingFor>
    <RelatedLinks>
      <Link>
        <URI>
          <link internal="true" type="WEAK">
            <target><![CDATA[/sites/default/opencms-documentation/content-in-opencms/lists-and-detail-pages/]]></target>
            <uuid>ff191c6a-3c1b-11e9-9d3e-0242ac11002b</uuid>
          </link>
        </URI>
        <LinkText><![CDATA[Overview on lists and detail pages]]></LinkText>
      </Link>
      <Link>
        <URI>
          <link internal="true" type="WEAK">
            <target><![CDATA[/sites/default/opencms-documentation/creating-a-website/creating-a-template-jsp/advanced-template-features/meta-mappings/]]></target>
            <uuid>97783758-f2f4-11e8-a09c-0242ac11002b</uuid>
          </link>
        </URI>
        <LinkText><![CDATA[Meta mappings]]></LinkText>
        <LinkDescription name="LinkDescription0">
          <links/>
          <content><![CDATA[<p>Provide information from the content in your template JSP before the content is rendered, i.e., text and images for meta tags in the HTML head used for social media.</p>]]></content>
        </LinkDescription>
      </Link>
      <LinkList>
        <Title><![CDATA[Examples for Lists with links to detail pages]]></Title>
        <Link>
          <URI>
            <link internal="true" type="WEAK">
              <target><![CDATA[/sites/default/opencms-documentation/demos/lists-and-detail-pages-iii/]]></target>
              <uuid>bd5d897c-3e45-11e9-9d3e-0242ac11002b</uuid>
            </link>
          </URI>
          <LinkText><![CDATA[Demo on lists with the OpenCms list type and detail pages (since OpenCms 11.0)]]></LinkText>
        </Link>
        <Link>
          <URI>
            <link internal="true" type="WEAK">
              <target><![CDATA[/sites/default/opencms-documentation/demos/lists-and-detail-pages-ii/]]></target>
              <uuid>9e541dcf-eb4d-11e5-b021-0242ac11002b</uuid>
            </link>
          </URI>
          <LinkText><![CDATA[Demo on lists and detail pages (since OpenCms 10.0)]]></LinkText>
        </Link>
        <Link>
          <URI>
            <link internal="true" type="WEAK">
              <target><![CDATA[/sites/default/opencms-documentation/demos/lists-and-detail-pages/]]></target>
              <uuid>017a27d0-22c2-11e4-8f7a-d9f74955ba1b</uuid>
            </link>
          </URI>
          <LinkText><![CDATA[Demo on lists and detail pages (traditional way, with &lt;cms:contentload&gt;)]]></LinkText>
        </Link>
      </LinkList>
    </RelatedLinks>
    <NewInVersion><![CDATA[6.0]]></NewInVersion>
    <NewInDocuVersion><![CDATA[9.0]]></NewInDocuVersion>
    <RevisedForVersion><![CDATA[11.0.0]]></RevisedForVersion>
    <StatusMetaData>
      <Todos/>
    </StatusMetaData>
  </AlkaconDocumentationTopicFrame>
</AlkaconDocumentationTopicFrames>
