<?xml version="1.0" encoding="UTF-8"?>

<DocumentationFigures xmlns:xsi="http://www.w3.org/2001/XMLSchema-instance" xsi:noNamespaceSchemaLocation="opencms://system/modules/com.alkacon.opencms.documentation/schemas/documentation-figure.xsd">
  <DocumentationFigure language="en">
    <Identifier><![CDATA[A]]></Identifier>
    <Title><![CDATA[Standard Layout Group Formatter of the Mercury Template]]></Title>
    <Image>
      <link type="WEAK">
        <target><![CDATA[/sites/default/opencms-documentation/.galleries/pictures/mercury-template-layout-group-formatter.png]]></target>
        <uuid>0a62d9db-b64d-11ec-adc5-0242ac11002b</uuid>
      </link>
    </Image>
    <OpenCmsVersion><![CDATA[12.0]]></OpenCmsVersion>
  </DocumentationFigure>
</DocumentationFigures>
