<?xml version="1.0" encoding="UTF-8"?>

<DocumentationDefinitionLists xmlns:xsi="http://www.w3.org/2001/XMLSchema-instance" xsi:noNamespaceSchemaLocation="opencms://system/modules/com.alkacon.opencms.documentation/schemas/documentation-definition-list.xsd">
  <DocumentationDefinitionList language="en">
    <Title><![CDATA[RequestContextBean: Useful properties of general interest]]></Title>
    <Heading><![CDATA[List of properties of general interest]]></Heading>
    <PropertyDef>true</PropertyDef>
    <Entry>
      <Term><![CDATA[uri]]></Term>
      <Description name="Description0">
        <links/>
        <content><![CDATA[<p>Returns the OpenCms VFS URI of the requested resource.</p>]]></content>
      </Description>
    </Entry>
  </DocumentationDefinitionList>
</DocumentationDefinitionLists>
