<?xml version="1.0" encoding="UTF-8"?>

<DocumentationTopicrows xmlns:xsi="http://www.w3.org/2001/XMLSchema-instance" xsi:noNamespaceSchemaLocation="opencms://system/modules/com.alkacon.opencms.documentation/schemas/documentation-topic-row.xsd">
  <DocumentationTopicrow language="en">
    <Title><![CDATA[The ADE views]]></Title>
    <Description name="Description0">
      <links/>
      <content><![CDATA[<p>The "Advanced direct edit" views are comfortable editors to manipulate single pages and the site structure. If a page is once set up, the ADE views suffice for most tasks. Content editors will see only ADE views - and maybe not even all of them. Only for administrative tasks, the traditional workplace has to be opened.</p>]]></content>
    </Description>
    <Item>
      <Headline/>
      <Topic>
        <PageLink>
          <link type="WEAK">
            <target><![CDATA[/sites/default/opencms-documentation/views-in-opencms/the-page-editor/]]></target>
            <uuid>772a450b-02c1-11e4-8167-1305b26fecac</uuid>
          </link>
        </PageLink>
      </Topic>
      <Topic>
        <PageLink>
          <link type="WEAK">
            <target><![CDATA[/sites/default/opencms-documentation/views-in-opencms/the-sitemap-editor/]]></target>
            <uuid>270e7393-06a0-11e4-909a-1305b26fecac</uuid>
          </link>
        </PageLink>
      </Topic>
      <Topic>
        <PageLink>
          <link type="WEAK">
            <target><![CDATA[/sites/default/opencms-documentation/views-in-opencms/the-content-editor/]]></target>
            <uuid>00a4c7ee-0812-11e4-8e56-b7bfd6088c56</uuid>
          </link>
        </PageLink>
      </Topic>
      <Topic>
        <PageLink>
          <link type="WEAK">
            <target><![CDATA[/sites/default/opencms-documentation/views-in-opencms/the-inline-editor/]]></target>
            <uuid>80930cc6-0b4f-11e4-8c80-b7bfd6088c56</uuid>
          </link>
        </PageLink>
      </Topic>
    </Item>
  </DocumentationTopicrow>
</DocumentationTopicrows>
