<?xml version="1.0" encoding="UTF-8"?>

<AlkaconDocumentationGlossarEntrys xmlns:xsi="http://www.w3.org/2001/XMLSchema-instance" xsi:noNamespaceSchemaLocation="opencms://system/modules/com.alkacon.opencms.documentation/schemas/documentation-glossar-entry.xsd">
  <AlkaconDocumentationGlossarEntry language="en">
    <Term><![CDATA[index field]]></Term>
    <RefId><![CDATA[index_field]]></RefId>
    <Match>
      <MatchString><![CDATA[index field]]></MatchString>
    </Match>
    <Match>
      <MatchString><![CDATA[index fields]]></MatchString>
    </Match>
    <Description name="Description0">
      <links/>
      <content><![CDATA[<p>'Index field' describes a field of a search index. Depending on the search engine used, it refers to a Solr field or a Lucene field.</p>]]></content>
    </Description>
  </AlkaconDocumentationGlossarEntry>
</AlkaconDocumentationGlossarEntrys>
