<?xml version="1.0" encoding="UTF-8"?>

<ExtendedSectionData xmlns:xsi="http://www.w3.org/2001/XMLSchema-instance" xsi:noNamespaceSchemaLocation="opencms://system/modules/alkacon.mercury.extension.section_ext/schemas/section-ext.xsd">
  <ExtendedSection language="en">
    <Title><![CDATA[Short-cut syntax for the most relevant search settings 2]]></Title>
    <Section>
      <Text name="Text0">
        <links>
          <link name="link0" internal="false" type="A">
            <target><![CDATA[https://github.com/alkacon/opencms-core/blob/branch_11_0_x/src/org/opencms/xml/content/simple-searchsetting-configs.st]]></target>
          </link>
        </links>
        <content><![CDATA[<div class="alert alert-info">The special short-cuts for listdate, listorder and listtitle are translated to normal searchsetting nodes via string template as defined <a href="%(link0)">here</a>.</div>]]></content>
      </Text>
    </Section>
  </ExtendedSection>
</ExtendedSectionData>
