<?xml version="1.0" encoding="UTF-8"?>

<ExtendedSectionData xmlns:xsi="http://www.w3.org/2001/XMLSchema-instance" xsi:noNamespaceSchemaLocation="opencms://system/modules/alkacon.mercury.extension.section_ext/schemas/section-ext.xsd">
  <ExtendedSection language="en">
    <Title><![CDATA[New extended content section]]></Title>
    <Section>
      <Text name="Text0">
        <links>
          <link name="link0" internal="true" type="A">
            <target><![CDATA[/sites/docu/opencms-documentation/background/the-virtual-file-system/]]></target>
            <uuid>711b44d5-d1b9-11ec-9238-0242ac11002b</uuid>
          </link>
          <link name="link1" internal="true" type="A">
            <target><![CDATA[/sites/docu/opencms-documentation/background/the-module-system/]]></target>
            <uuid>8d7dcf6b-d1b9-11ec-9238-0242ac11002b</uuid>
          </link>
          <link name="link2" internal="true" type="A">
            <target><![CDATA[/sites/docu/opencms-documentation/the-opencms-workplace/websites-app/]]></target>
            <uuid>0330a7bd-d1c7-11ec-9238-0242ac11002b</uuid>
          </link>
        </links>
        <content><![CDATA[<p>The above example JSP saved in an arbitrary directory of the <a href="%(link0)">OpenCms virtual file system</a>, e.g., at <code>/system/examples/hello.jsp</code>, will render the following HTML page:</p>
<ul>
<li>the numbers 1 to 10 as an unordered list</li>
<li>the current date in a formatted way</li>
<li>the string "Hello JSP" in upper case</li>
<li>the current version of the OpenCms servlet</li>
</ul>
<p>Template JSPs are stored in <a href="%(link1)">Modules</a>, by convention in a folder called <code>templates/</code>. Say there is a module named <code>org.opencms.examples</code>, then the template would be saved at <code>/system/modules/org.opencms.examples/templates/</code> in the virtual file system of OpenCms.</p>
<p>OpenCms provides a special resource type called <strong>Page template</strong> for template JSPs. It is good practice to give your template JSP the special page template type since, if a content administrator creates a new website with the <a href="%(link2)">Websites app</a>, all page templates appear in the drop-down list, whilst normal JSP do not appear here.</p>]]></content>
      </Text>
    </Section>
  </ExtendedSection>
</ExtendedSectionData>
