<?xml version="1.0" encoding="UTF-8"?>

<ExtendedSectionData xmlns:xsi="http://www.w3.org/2001/XMLSchema-instance" xsi:noNamespaceSchemaLocation="opencms://system/modules/alkacon.mercury.extension.section_ext/schemas/section-ext.xsd">
  <ExtendedSection language="en">
    <Title><![CDATA[Defining the visibility of a schema element]]></Title>
    <Section>
      <Text name="Text0">
        <links/>
        <content><![CDATA[<p>Which schema element should be visible to which users is defined in the schema definition (XSD) in the section <code>xsd:annotation/xsd:appinfo</code>. Using the <code>&lt;visibility&gt;</code> node, you can define when a content element should be shown in the content editor. A possible configuration could look like:</p>]]></content>
      </Text>
    </Section>
  </ExtendedSection>
</ExtendedSectionData>
