<?xml version="1.0" encoding="UTF-8"?>

<ExtendedSectionData xmlns:xsi="http://www.w3.org/2001/XMLSchema-instance" xsi:noNamespaceSchemaLocation="opencms://system/modules/alkacon.mercury.extension.section_ext/schemas/section-ext.xsd">
  <ExtendedSection language="en">
    <Title><![CDATA[Tab configuration]]></Title>
    <Section>
      <Text name="Text0">
        <links/>
        <content><![CDATA[<p>The form-based content editor allows content fields to be organized in tabs. Which field is shown in which tab can be configured in the content schema document.</p>]]></content>
      </Text>
    </Section>
  </ExtendedSection>
</ExtendedSectionData>
