<?xml version="1.0" encoding="UTF-8"?>

<ExtendedSectionData xmlns:xsi="http://www.w3.org/2001/XMLSchema-instance" xsi:noNamespaceSchemaLocation="opencms://system/modules/alkacon.mercury.extension.section_ext/schemas/section-ext.xsd">
  <ExtendedSection language="en">
    <Title><![CDATA[Configuration for the single-tree approach 5]]></Title>
    <Section>
      <Text name="Text0">
        <links/>
        <content><![CDATA[<p>To configure link substitution for the single-tree approach, edit the <code>opencms-importexport.xml</code> and substitute</p>]]></content>
      </Text>
    </Section>
  </ExtendedSection>
</ExtendedSectionData>
