<?xml version="1.0" encoding="UTF-8"?>

<ExtendedSectionData xmlns:xsi="http://www.w3.org/2001/XMLSchema-instance" xsi:noNamespaceSchemaLocation="opencms://system/modules/alkacon.mercury.extension.section_ext/schemas/section-ext.xsd">
  <ExtendedSection language="en">
    <Title><![CDATA[ How to open the "Edit properties" dialog]]></Title>
    <Section>
      <Text name="Text0">
        <links>
          <link name="link0" internal="true" type="A">
            <target><![CDATA[/sites/docu/opencms-documentation/todo/the-opencms-workplace/editors/the-page-editor/]]></target>
            <uuid>0597a70a-d1c5-11ec-9238-0242ac11002b</uuid>
          </link>
          <link name="link1" internal="true" type="A">
            <target><![CDATA[/sites/docu/opencms-documentation/todo/the-opencms-workplace/editors/the-sitemap-editor/]]></target>
            <uuid>0d5f13cb-d1c5-11ec-9238-0242ac11002b</uuid>
          </link>
          <link name="link2" internal="true" type="A">
            <target><![CDATA[/sites/docu/opencms-documentation/todo/the-opencms-workplace/launchpad-and-other-apps/explorer/]]></target>
            <uuid>71c1c77d-d1c5-11ec-9238-0242ac11002b</uuid>
          </link>
        </links>
        <content><![CDATA[<p>The properties dialog can be opened from various places:</p>
<ul>
<li><em><a href="%(link0)">The page editor</a></em>: Press "Properties" in the Context menu exposed via the editor toolbar to edit the properties of the current container page.</li>
<li><em><a href="%(link1)">The sitemap editor</a></em>: Press "Properties" in the context menu of the sitemap or the single pages. <strong>Be aware that you edit the properties of folder and container page in the default sitemap editor view.</strong></li>
<li><em><a href="%(link2)">The explorer app</a></em>: Right-click on a resource and choose "Properties" to edit the properties for a resource.</li>
</ul>]]></content>
      </Text>
    </Section>
  </ExtendedSection>
</ExtendedSectionData>
