<?xml version="1.0" encoding="UTF-8"?>

<DocumentationCodeBlocks xmlns:xsi="http://www.w3.org/2001/XMLSchema-instance" xsi:noNamespaceSchemaLocation="opencms://system/modules/com.alkacon.opencms.documentation/schemas/documentation-codeblock.xsd">
  <DocumentationCodeBlock language="en">
    <Code><![CDATA[...
  <xsd:complexType name="OpenCmsDevDemoSettingsArticle">
    <xsd:sequence>
      ...
      <xsd:element name="Options" type="OpenCmsDevDemoTextOption" minOccurs="0" />
      ... 
    </xsd:sequence>
...]]></Code>
  </DocumentationCodeBlock>
</DocumentationCodeBlocks>
